<annotation>
	<folder>pics</folder>
	<filename>8.jpg</filename>
	<path>/home/agent/Estudiar/DeepLearning/Project/detect/img/pics/8.jpg</path>
	<source>
		<database>Unknown</database>
	</source>
	<size>
		<width>640</width>
		<height>360</height>
		<depth>3</depth>
	</size>
	<segmented>0</segmented>
	<object>
		<name>toilet</name>
		<pose>Unspecified</pose>
		<truncated>0</truncated>
		<difficult>0</difficult>
		<bndbox>
			<xmin>127</xmin>
			<ymin>7</ymin>
			<xmax>379</xmax>
			<ymax>223</ymax>
		</bndbox>
	</object>
</annotation>
